diffkalman/__init__.py
diffkalman/em_loop.py
diffkalman/filter.py
diffkalman/joint_jacobian_transform.py
diffkalman/negative_log_likelihood.py
diffkalman/py.typed
diffkalman/utils.py
diffkalman-0.1.1.dist-info/METADATA
diffkalman-0.1.1.dist-info/WHEEL
diffkalman-0.1.1.dist-info/licenses/LICENSE
diffkalman-0.1.1.dist-info/RECORD
