Metadata-Version: 2.4
Name: diffkalman
Version: 0.1.1
Summary: A diffrentiable kalman filter library for auto-tuning kalman filters.
Author-email: hades <nischalbhattaraipi@gmail.com>
License-File: LICENSE
Requires-Python: >=3.11
Requires-Dist: numpy>=2.2.1
Requires-Dist: tqdm>=4.67.1
Provides-Extra: cpu
Requires-Dist: torch>=2.5.1; extra == 'cpu'
Provides-Extra: cu124
Requires-Dist: torch>=2.5.1; extra == 'cu124'
